Metadata-Version: 2.1
Name: flake8-commas
Version: 4.0.0
Summary: Flake8 lint for trailing commas.
Home-page: https://github.com/PyCQA/flake8-commas/
Author: Trevor Creech
Author-email: trevor@trevorcreech.com
Maintainer: Peter Law
Maintainer-email: PeterJCLaw@gmail.com
Classifier: Environment :: Console
Classifier: Intended Audience :: Developers
Classifier: Operating System :: OS Independent
Classifier: License :: OSI Approved :: MIT License
Classifier: Programming Language :: Python
Classifier: Programming Language :: Python :: 3.8
Classifier: Programming Language :: Python :: 3.9
Classifier: Programming Language :: Python :: 3.10
Classifier: Programming Language :: Python :: 3.11
Classifier: Programming Language :: Python :: 3.12
Classifier: Topic :: Software Development :: Libraries :: Python Modules
Classifier: Topic :: Software Development :: Quality Assurance
Classifier: Framework :: Flake8
Requires-Python: >=3.8
License-File: LICENSE
Requires-Dist: flake8>=5
